singletonify/__init__.py
singletonify-0.2.4.dist-info/LICENSE
singletonify-0.2.4.dist-info/METADATA
singletonify-0.2.4.dist-info/WHEEL
singletonify-0.2.4.dist-info/top_level.txt
singletonify-0.2.4.dist-info/RECORD
