Metadata-Version: 1.0
Name: singletonify
Version: 0.2.4
Summary: UNKNOWN
Home-page: https://github.com/Cologler/singletonify-python
Author: cologler
Author-email: skyoflw@gmail.com
License: MIT License
Keywords: singleton
Platform: UNKNOWN
